{
    "project": {
        "name": "davinci-blade",
        "description": "TypeScript Geometric Physics library.",
        "version": "0.9.15",
        "url": "",
        "logo": "../assets/logo.png"
    },
    "files": {
        "amd/davinci-blade/Dimensions.js": {
            "name": "amd/davinci-blade/Dimensions.js",
            "modules": {},
            "classes": {
                "Dimensions": 1
            },
            "fors": {},
            "namespaces": {}
        },
        "amd/davinci-blade/Euclidean2.js": {
            "name": "amd/davinci-blade/Euclidean2.js",
            "modules": {},
            "classes": {
                "Euclidean2": 1
            },
            "fors": {},
            "namespaces": {}
        },
        "amd/davinci-blade/Euclidean3.js": {
            "name": "amd/davinci-blade/Euclidean3.js",
            "modules": {},
            "classes": {
                "Euclidean3": 1
            },
            "fors": {},
            "namespaces": {}
        },
        "amd/davinci-blade/Measure.js": {
            "name": "amd/davinci-blade/Measure.js",
            "modules": {},
            "classes": {
                "Measure": 1
            },
            "fors": {},
            "namespaces": {}
        },
        "amd/davinci-blade/Rational.js": {
            "name": "amd/davinci-blade/Rational.js",
            "modules": {},
            "classes": {
                "Rational": 1
            },
            "fors": {},
            "namespaces": {}
        },
        "amd/davinci-blade/Unit.js": {
            "name": "amd/davinci-blade/Unit.js",
            "modules": {},
            "classes": {
                "Unit": 1
            },
            "fors": {},
            "namespaces": {}
        },
        "amd/davinci-blade.js": {
            "name": "amd/davinci-blade.js",
            "modules": {
                "blade": 1
            },
            "classes": {},
            "fors": {},
            "namespaces": {}
        }
    },
    "modules": {
        "blade": {
            "name": "blade",
            "submodules": {},
            "classes": {
                "Dimensions": 1,
                "Euclidean2": 1,
                "Euclidean3": 1,
                "Measure": 1,
                "Rational": 1,
                "Unit": 1
            },
            "fors": {},
            "namespaces": {},
            "tag": "module",
            "file": "amd/davinci-blade/Unit.js",
            "line": 111,
            "description": "Provides the blade module"
        }
    },
    "classes": {
        "Dimensions": {
            "name": "Dimensions",
            "shortname": "Dimensions",
            "classitems": [],
            "plugins": [],
            "extensions": [],
            "plugin_for": [],
            "extension_for": [],
            "module": "blade",
            "file": "amd/davinci-blade/Dimensions.js",
            "line": 3,
            "description": "The Dimensions class captures the physical dimensions associated with a unit of measure.",
            "is_constructor": 1,
            "params": [
                {
                    "name": "mass",
                    "description": "The mass component of the dimensions object.",
                    "type": "Rational"
                },
                {
                    "name": "length",
                    "description": "The length component of the dimensions object.",
                    "type": "Rational"
                },
                {
                    "name": "time",
                    "description": "The time component of the dimensions object.",
                    "type": "Rational"
                },
                {
                    "name": "charge",
                    "description": "The charge component of the dimensions object.",
                    "type": "Rational"
                },
                {
                    "name": "temperature",
                    "description": "The temperature component of the dimensions object.",
                    "type": "Rational"
                },
                {
                    "name": "amount",
                    "description": "The amount component of the dimensions object.",
                    "type": "Rational"
                },
                {
                    "name": "intensity",
                    "description": "The intensity component of the dimensions object.",
                    "type": "Rational"
                }
            ]
        },
        "Euclidean2": {
            "name": "Euclidean2",
            "shortname": "Euclidean2",
            "classitems": [],
            "plugins": [],
            "extensions": [],
            "plugin_for": [],
            "extension_for": [],
            "module": "blade",
            "file": "amd/davinci-blade/Euclidean2.js",
            "line": 351,
            "description": "The Euclidean2 class represents a multivector for a 2-dimensional linear space with a Euclidean metric.",
            "is_constructor": 1,
            "params": [
                {
                    "name": "w",
                    "description": "The scalar part of the multivector.",
                    "type": "Number"
                },
                {
                    "name": "x",
                    "description": "The vector component of the multivector in the x-direction.",
                    "type": "Number"
                },
                {
                    "name": "y",
                    "description": "The vector component of the multivector in the y-direction.",
                    "type": "Number"
                },
                {
                    "name": "xy",
                    "description": "The pseudoscalar part of the multivector.",
                    "type": "Number"
                }
            ]
        },
        "Euclidean3": {
            "name": "Euclidean3",
            "shortname": "Euclidean3",
            "classitems": [],
            "plugins": [],
            "extensions": [],
            "plugin_for": [],
            "extension_for": [],
            "module": "blade",
            "file": "amd/davinci-blade/Euclidean3.js",
            "line": 542,
            "description": "The Euclidean3 class represents a multivector for a 3-dimensional linear space with a Euclidean metric.",
            "is_constructor": 1,
            "params": [
                {
                    "name": "w",
                    "description": "The scalar part of the multivector.",
                    "type": "Number"
                },
                {
                    "name": "x",
                    "description": "The vector component of the multivector in the x-direction.",
                    "type": "Number"
                },
                {
                    "name": "y",
                    "description": "The vector component of the multivector in the y-direction.",
                    "type": "Number"
                },
                {
                    "name": "z",
                    "description": "The vector component of the multivector in the z-direction.",
                    "type": "Number"
                },
                {
                    "name": "xy",
                    "description": "The bivector component of the multivector in the xy-plane.",
                    "type": "Number"
                },
                {
                    "name": "yz",
                    "description": "The bivector component of the multivector in the yz-plane.",
                    "type": "Number"
                },
                {
                    "name": "zx",
                    "description": "The bivector component of the multivector in the zx-plane.",
                    "type": "Number"
                },
                {
                    "name": "xyz",
                    "description": "The pseudoscalar part of the multivector.",
                    "type": "Number"
                }
            ]
        },
        "Measure": {
            "name": "Measure",
            "shortname": "Measure",
            "classitems": [],
            "plugins": [],
            "extensions": [],
            "plugin_for": [],
            "extension_for": [],
            "module": "blade",
            "file": "amd/davinci-blade/Measure.js",
            "line": 3,
            "description": "A Measure is a composite consisting of a quantity and a unit of measure.",
            "is_constructor": 1,
            "params": [
                {
                    "name": "quantity",
                    "description": "The <em>quantity</em> part of the measure.",
                    "type": "QuantityOfMeasure<T>"
                },
                {
                    "name": "uom",
                    "description": "The unit-of-measure part of the measure.",
                    "type": "Unit"
                }
            ]
        },
        "Rational": {
            "name": "Rational",
            "shortname": "Rational",
            "classitems": [],
            "plugins": [],
            "extensions": [],
            "plugin_for": [],
            "extension_for": [],
            "module": "blade",
            "file": "amd/davinci-blade/Rational.js",
            "line": 3,
            "description": "The Rational class represents a rational number.",
            "extends": "Field",
            "is_constructor": 1,
            "params": [
                {
                    "name": "n",
                    "description": "The numerator.",
                    "type": "Number"
                },
                {
                    "name": "d",
                    "description": "The denominator.",
                    "type": "Number"
                }
            ]
        },
        "Unit": {
            "name": "Unit",
            "shortname": "Unit",
            "classitems": [],
            "plugins": [],
            "extensions": [],
            "plugin_for": [],
            "extension_for": [],
            "module": "blade",
            "file": "amd/davinci-blade/Unit.js",
            "line": 111,
            "description": "The Unit class represents the units for a measure.",
            "is_constructor": 1,
            "params": [
                {
                    "name": "scale",
                    "description": "",
                    "type": "Number"
                },
                {
                    "name": "dimensions",
                    "description": "",
                    "type": "Dimensions"
                },
                {
                    "name": "labels",
                    "description": "The label strings to use for each dimension.",
                    "type": "String[]"
                }
            ]
        }
    },
    "classitems": [
        {
            "file": "amd/davinci-blade/Dimensions.js",
            "line": 118,
            "description": "The <em>mass</em> component of this dimensions instance.",
            "itemtype": "property",
            "name": "M",
            "type": "{Rational}",
            "class": "Dimensions"
        },
        {
            "file": "amd/davinci-blade/Dimensions.js",
            "line": 153,
            "description": "Determines whether all the components of the Dimensions instance are zero.",
            "itemtype": "method",
            "name": "isZero",
            "return": {
                "description": "<code>true</code> if all the components are zero, otherwise <code>false</code>.",
                "type": "Boolean"
            },
            "class": "Dimensions"
        },
        {
            "file": "amd/davinci-blade/Euclidean3.js",
            "line": 162,
            "class": "Euclidean3"
        },
        {
            "file": "amd/davinci-blade/Measure.js",
            "line": 22,
            "description": "The quantity part of the measure.",
            "itemtype": "property",
            "name": "quantity",
            "type": "{GeometricQuantity<T>}",
            "class": "Measure"
        },
        {
            "file": "amd/davinci-blade/Measure.js",
            "line": 35,
            "description": "The unit part of the measure.",
            "itemtype": "property",
            "name": "uom",
            "type": "{Unit}",
            "class": "Measure"
        },
        {
            "file": "amd/davinci-blade/Rational.js",
            "line": 55,
            "description": "The numerator part of the rational number.",
            "itemtype": "property",
            "name": "numer",
            "type": "{number}",
            "class": "Rational"
        },
        {
            "file": "amd/davinci-blade/Rational.js",
            "line": 68,
            "description": "The denominator part of the rational number.",
            "itemtype": "property",
            "name": "denom",
            "type": "{number}",
            "class": "Rational"
        },
        {
            "file": "amd/davinci-blade/Rational.js",
            "line": 80,
            "description": "Returns the sum of this rational number and the argument.",
            "itemtype": "method",
            "name": "add",
            "params": [
                {
                    "name": "rhs",
                    "description": "The number used on the right hand side of the addition operator.",
                    "type": "Number|Rational"
                }
            ],
            "return": {
                "description": "The sum of this rational number and the specified argument.",
                "type": "Rational"
            },
            "class": "Rational"
        },
        {
            "file": "amd/davinci-blade/Rational.js",
            "line": 95,
            "description": "Returns the difference of this rational number and the argument.",
            "itemtype": "method",
            "name": "sub",
            "params": [
                {
                    "name": "rhs",
                    "description": "The number used on the right hand side of the subtraction operator.",
                    "type": "Number|Rational"
                }
            ],
            "return": {
                "description": "The difference of this rational number and the specified argument.",
                "type": "Rational"
            },
            "class": "Rational"
        },
        {
            "file": "amd/davinci-blade.js",
            "line": 46,
            "description": "A dimensionless unit.",
            "itemtype": "property",
            "name": "UNIT_DIMLESS",
            "type": "Unit",
            "static": 1,
            "final": 1,
            "class": "",
            "module": "blade"
        }
    ],
    "warnings": [
        {
            "message": "Missing item type",
            "line": " amd/davinci-blade/Euclidean3.js:162"
        }
    ]
}